README.md
setup.py
flash_attention_x/__init__.py
flash_attention_x/flash_attention_causal.py
flash_attention_x/flash_attention_causal_og.py
flash_attention_x.egg-info/PKG-INFO
flash_attention_x.egg-info/SOURCES.txt
flash_attention_x.egg-info/dependency_links.txt
flash_attention_x.egg-info/requires.txt
flash_attention_x.egg-info/top_level.txt