Metadata-Version: 2.1
Name: flash-attention-x
Version: 0.0.1
Summary: A flash attention(s) implementation in triton.
Home-page: https://github.com/ahxt/flash-attention-x
Author: Xiaotian Han
Author-email: your.email@example.com
Classifier: Programming Language :: Python :: 3
Classifier: License :: OSI Approved :: MIT License
Classifier: Operating System :: OS Independent
Requires-Python: >=3.8
